orchestrator/__init__.py
orchestrator/__main__.py
orchestrator/cli.py
orchestrator/conditions.py
orchestrator/config.py
orchestrator/context.py
orchestrator/display.py
orchestrator/selector.py
orchestrator/tmux.py
orchestrator/workflow.py
orchestrator/linear/__init__.py
orchestrator/linear/client.py
orchestrator/linear/queries.py
orchestrator/linear/types.py
orchestrator/tools/__init__.py
orchestrator/tools/base.py
orchestrator/tools/bash.py
orchestrator/tools/break_tool.py
orchestrator/tools/claude.py
orchestrator/tools/claude_sdk.py
orchestrator/tools/continue_tool.py
orchestrator/tools/foreach.py
orchestrator/tools/goto.py
orchestrator/tools/linear_manage.py
orchestrator/tools/linear_tasks.py
orchestrator/tools/set.py
claude_workflow-0.1.0.dist-info/METADATA
claude_workflow-0.1.0.dist-info/WHEEL
claude_workflow-0.1.0.dist-info/entry_points.txt
claude_workflow-0.1.0.dist-info/licenses/LICENSE
claude_workflow-0.1.0.dist-info/RECORD
