Metadata-Version: 2.4
Name: claude-workflow
Version: 0.1.0
Summary: A terminal-based orchestrator for running Claude Code workflows defined in YAML files
Project-URL: Homepage, https://github.com/michalkatanski/claude-workflow
Project-URL: Repository, https://github.com/michalkatanski/claude-workflow
Project-URL: Issues, https://github.com/michalkatanski/claude-workflow/issues
Author: Michal Katanski
License: MIT
License-File: LICENSE
Keywords: automation,claude,orchestrator,tmux,workflow
Classifier: Development Status :: 4 - Beta
Classifier: Environment :: Console
Classifier: Intended Audience :: Developers
Classifier: License :: OSI Approved :: MIT License
Classifier: Operating System :: MacOS
Classifier: Operating System :: POSIX :: Linux
Classifier: Programming Language :: Python :: 3
Classifier: Programming Language :: Python :: 3.11
Classifier: Programming Language :: Python :: 3.12
Classifier: Programming Language :: Python :: 3.13
Classifier: Topic :: Software Development :: Build Tools
Classifier: Topic :: Utilities
Requires-Python: >=3.11
Requires-Dist: claude-agent-sdk>=0.1.0
Requires-Dist: claude-code-tools>=0.1.0
Requires-Dist: httpx>=0.25.0
Requires-Dist: pyyaml>=6.0
Requires-Dist: questionary>=2.0.0
Requires-Dist: rich>=13.0.0
